kw_notebook_core/__init__.py
kw_notebook_core/admonition.py
kw_notebook_core/bokeh.py
kw_notebook_core/display.py
kw_notebook_core-0.0.27.dist-info/LICENSE
kw_notebook_core-0.0.27.dist-info/METADATA
kw_notebook_core-0.0.27.dist-info/WHEEL
kw_notebook_core-0.0.27.dist-info/top_level.txt
kw_notebook_core-0.0.27.dist-info/RECORD
