Metadata-Version: 2.1
Name: kw-notebook-core
Version: 0.0.27
Summary: Ken's convenience tool for JupyterLab notebooks and Google Colaboratory notebooks
Home-page: https://github.com/wakita/kw_notebook_core
Author: Ken Wakita
Author-email: wakita@is.titech.ac.jp
Project-URL: Bug Tracker, https://github.com/wakita/kw_notebook_core/issues
Classifier: Programming Language :: Python :: 3
Classifier: License :: OSI Approved :: MIT License
Classifier: Operating System :: OS Independent
Requires-Python: >=3.6
License-File: LICENSE
